{
    "Nasdaq":[
        {
        "value": 14430.00
        },
        {
        "value": 14500.00
        },
        {
        "value": 16000.00
        },
        {
        "value": 16323.00
        },
        {
        "value": 15735.00
        },
        {
        "value": 16816.00
        },
        {
        "value": 15736.00
        },
        {
        "value": 14234.00
        },
        {
        "value": 13245.00
        },
        {
        "value": 12387.00
        },
        {
        "value": 12837.00
        },
        {
        "value": 12973.00
        }
    ],
    "SP500":[
        {
        "value": 4362.00
        },
        {
        "value": 4388.00
        },
        {
        "value": 4736.00
        },
        {
        "value": 4673.00
        },
        {
        "value": 4987.00
        },
        {
        "value": 5032.00
        },
        {
        "value": 5012.00
        },
        {
        "value": 4823.00
        },
        {
        "value": 4728.00
        },
        {
        "value": 4927.00
        },
        {
        "value": 4532.00
        },
        {
        "value": 4322.00
        }
    ],
    "FTSE":[
        {
        "value": 7421.00
        },
        {
        "value": 7499.00
        },
        {
        "value": 7586.00
        },
        {
        "value": 7427.00
        },
        {
        "value": 7421.00
        },
        {
        "value": 7387.00
        },
        {
        "value": 7366.00
        },
        {
        "value": 7465.00
        },
        {
        "value": 7533.00
        },
        {
        "value": 7586.00
        },
        {
        "value": 7599.00
        },
        {
        "value": 7693.00
        }
    ],
    "xLabel":[
        "Aug",
        "Sept",
        "Oct",
        "Nov",
        "Dec",
        "Jan",
        "Feb",
        "Mar",
        "Apr",
        "May",
        "Jun",
        "Jul"
    ]
}